{
  "_class": "group",
  "do_objectID": "E16EB9C2-0929-4764-AAA3-2AE2132F9F6B",
  "exportOptions": {
    "_class": "exportOptions",
    "exportFormats": [
    ],
    "includedLayerIds": [
    ],
    "layerOptions": 0,
    "shouldTrim": false
  },
  "frame": {
    "_class": "rect",
    "constrainProportions": false,
    "height": 182,
    "width": 264,
    "x": 30,
    "y": 91
  },
  "hasClickThrough": false,
  "isFlippedHorizontal": false,
  "isFlippedVertical": false,
  "isLocked": false,
  "isVisible": true,
  "layerListExpandedType": 2,
  "layers": [
    {
      "class": "group",
      "id": "FC720AE8-3A58-4787-A19E-1EEC5595FB7C"
    },
    {
      "class": "text",
      "id": "B24B71C3-849F-40D0-BD11-CD8A06A61D9E"
    },
    {
      "class": "group",
      "id": "FE58B8AF-F1C9-432A-8FCD-012E497F47BB"
    },
    {
      "class": "group",
      "id": "AEA5B75D-8013-490A-ADCF-78EC1B28A4F8"
    },
    {
      "class": "group",
      "id": "A86F7EAD-5C75-4CFC-AE90-3C2EB35DBCD2"
    },
    {
      "class": "group",
      "id": "9382E809-D335-4A42-9D13-558573D742F4"
    }
  ],
  "name": "Group 7 Copy",
  "nameIsFixed": false,
  "resizingConstraint": 63,
  "resizingType": 0,
  "rotation": 0,
  "shouldBreakMaskChain": false,
  "style": {
    "_class": "style",
    "endDecorationType": 0,
    "miterLimit": 10,
    "startDecorationType": 0
  }
}