{
  "_class": "group",
  "do_objectID": "83FCFA6D-8DA5-45F8-AF5D-CB06BE8F122D",
  "exportOptions": {
    "_class": "exportOptions",
    "exportFormats": [
    ],
    "includedLayerIds": [
    ],
    "layerOptions": 0,
    "shouldTrim": false
  },
  "frame": {
    "_class": "rect",
    "constrainProportions": false,
    "height": 40,
    "width": 202,
    "x": 54,
    "y": 395
  },
  "hasClickThrough": false,
  "isFlippedHorizontal": false,
  "isFlippedVertical": false,
  "isLocked": false,
  "isVisible": true,
  "layerListExpandedType": 0,
  "layers": [
    {
      "class": "shapeGroup",
      "id": "BD00D83A-E260-46E8-B646-960819B2C24E"
    },
    {
      "class": "shapeGroup",
      "id": "9861884C-1B29-40E3-802A-3C675B72242D"
    }
  ],
  "name": "Rectangle 7 + Triangle 2 Copy 8",
  "nameIsFixed": false,
  "resizingConstraint": 63,
  "resizingType": 0,
  "rotation": 0,
  "shouldBreakMaskChain": false,
  "style": {
    "_class": "style",
    "endDecorationType": 0,
    "miterLimit": 10,
    "startDecorationType": 0
  }
}