{
  "_class": "group",
  "do_objectID": "F2AC5FCD-1249-4A20-88B4-9E48E3D84C6D",
  "exportOptions": {
    "_class": "exportOptions",
    "exportFormats": [
    ],
    "includedLayerIds": [
    ],
    "layerOptions": 0,
    "shouldTrim": false
  },
  "frame": {
    "_class": "rect",
    "constrainProportions": false,
    "height": 18,
    "width": 18,
    "x": 36,
    "y": 200
  },
  "hasClickThrough": false,
  "isFlippedHorizontal": false,
  "isFlippedVertical": false,
  "isLocked": false,
  "isVisible": true,
  "layerListExpandedType": 0,
  "layers": [
    {
      "class": "shapeGroup",
      "id": "3B0C1884-96BE-4CF4-8875-E63C10DF268D"
    },
    {
      "class": "shapeGroup",
      "id": "D825AA9E-5716-460E-8A0B-79EFC176964F"
    }
  ],
  "name": "Group 2 Copy 3",
  "nameIsFixed": false,
  "resizingConstraint": 63,
  "resizingType": 0,
  "rotation": 0,
  "shouldBreakMaskChain": false,
  "style": {
    "_class": "style",
    "endDecorationType": 0,
    "miterLimit": 10,
    "startDecorationType": 0
  }
}