{
  "_class": "group",
  "do_objectID": "93EAE604-6AD1-4448-B21B-EF10F8F75992",
  "exportOptions": {
    "_class": "exportOptions",
    "exportFormats": [
    ],
    "includedLayerIds": [
    ],
    "layerOptions": 0,
    "shouldTrim": false
  },
  "frame": {
    "_class": "rect",
    "constrainProportions": false,
    "height": 18,
    "width": 18,
    "x": 12,
    "y": 70
  },
  "hasClickThrough": false,
  "isFlippedHorizontal": false,
  "isFlippedVertical": false,
  "isLocked": false,
  "isVisible": true,
  "layerListExpandedType": 0,
  "layers": [
    {
      "class": "shapeGroup",
      "id": "344548D8-E2C4-42CB-8216-1E4C7C2C247D"
    },
    {
      "class": "shapeGroup",
      "id": "0AF6B8DC-FF93-439E-AFA6-A1AEA17D6900"
    }
  ],
  "name": "Group 2 Copy 4",
  "nameIsFixed": false,
  "resizingConstraint": 63,
  "resizingType": 0,
  "rotation": 0,
  "shouldBreakMaskChain": false,
  "style": {
    "_class": "style",
    "endDecorationType": 0,
    "miterLimit": 10,
    "startDecorationType": 0
  }
}