{
  "_class": "group",
  "do_objectID": "3311EA63-22DC-4994-8AC0-EBB4F779EB4E",
  "exportOptions": {
    "_class": "exportOptions",
    "exportFormats": [
    ],
    "includedLayerIds": [
    ],
    "layerOptions": 0,
    "shouldTrim": false
  },
  "frame": {
    "_class": "rect",
    "constrainProportions": false,
    "height": 504,
    "width": 24,
    "x": 0,
    "y": 47
  },
  "hasClickThrough": false,
  "isFlippedHorizontal": false,
  "isFlippedVertical": false,
  "isLocked": false,
  "isVisible": true,
  "layerListExpandedType": 2,
  "layers": [
    {
      "class": "symbolInstance",
      "id": "F011AFD3-46C6-452D-89FA-38DEE3151B0C"
    },
    {
      "class": "symbolInstance",
      "id": "1D02B77D-D954-48D0-A5AC-ACD5A776A5D4"
    },
    {
      "class": "symbolInstance",
      "id": "E1289B2E-781E-4ED4-A9BD-FA68328D83C8"
    },
    {
      "class": "symbolInstance",
      "id": "B32915B4-103D-43C6-8937-0A34A89DCEEF"
    },
    {
      "class": "symbolInstance",
      "id": "E6CFB018-B446-434E-A6AD-924939B33847"
    },
    {
      "class": "symbolInstance",
      "id": "68023C4A-31FD-44FE-8BF1-8604742F41AD"
    },
    {
      "class": "symbolInstance",
      "id": "0BD16FF3-28BD-437A-9B96-2BDDB3C16F0D"
    },
    {
      "class": "symbolInstance",
      "id": "1F64C002-0973-4813-8D54-94851C8B1392"
    },
    {
      "class": "symbolInstance",
      "id": "2331D019-5C06-41FD-9F86-E848BC7F123F"
    },
    {
      "class": "group",
      "id": "F18E54A8-21F1-4045-AE32-3D6F0805A711"
    },
    {
      "class": "group",
      "id": "3C07D151-1416-498B-9A66-C3E80D5263D6"
    }
  ],
  "name": "Group Copy",
  "nameIsFixed": false,
  "resizingConstraint": 63,
  "resizingType": 0,
  "rotation": 0,
  "shouldBreakMaskChain": false,
  "style": {
    "_class": "style",
    "endDecorationType": 0,
    "miterLimit": 10,
    "startDecorationType": 0
  }
}