{
  "_class": "group",
  "do_objectID": "9F9DB178-50CC-4185-B64B-324F5BB5DC05",
  "exportOptions": {
    "_class": "exportOptions",
    "exportFormats": [
    ],
    "includedLayerIds": [
    ],
    "layerOptions": 0,
    "shouldTrim": false
  },
  "frame": {
    "_class": "rect",
    "constrainProportions": false,
    "height": 18,
    "width": 18,
    "x": 38,
    "y": 433
  },
  "hasClickThrough": false,
  "isFlippedHorizontal": false,
  "isFlippedVertical": false,
  "isLocked": false,
  "isVisible": true,
  "layerListExpandedType": 0,
  "layers": [
    {
      "class": "shapeGroup",
      "id": "9D9E1B67-F056-429F-8F43-14EFF8938D4D"
    },
    {
      "class": "shapeGroup",
      "id": "0136B02F-0364-4C72-AE6D-282B8A05A6C3"
    }
  ],
  "name": "Group 2 Copy 5",
  "nameIsFixed": false,
  "resizingConstraint": 63,
  "resizingType": 0,
  "rotation": 0,
  "shouldBreakMaskChain": false,
  "style": {
    "_class": "style",
    "endDecorationType": 0,
    "miterLimit": 10,
    "startDecorationType": 0
  }
}