{
  "_class": "group",
  "do_objectID": "3A4E1D4A-7DF7-4A6F-B019-B5EAE28DE858",
  "exportOptions": {
    "_class": "exportOptions",
    "exportFormats": [
    ],
    "includedLayerIds": [
    ],
    "layerOptions": 0,
    "shouldTrim": false
  },
  "frame": {
    "_class": "rect",
    "constrainProportions": true,
    "height": 21,
    "width": 75.19354838709677,
    "x": 25,
    "y": 41
  },
  "hasClickThrough": false,
  "isFlippedHorizontal": false,
  "isFlippedVertical": false,
  "isLocked": false,
  "isVisible": true,
  "layerListExpandedType": 0,
  "layers": [
    {
      "class": "shapeGroup",
      "id": "33FF0C93-B04B-47FB-848F-7462D6B7548B"
    },
    {
      "class": "shapeGroup",
      "id": "4B6B4FE8-84B4-49A5-95C1-CE7D407FC942"
    },
    {
      "class": "shapeGroup",
      "id": "2790A399-87E4-4037-9D91-A8F7B2EB724F"
    },
    {
      "class": "shapeGroup",
      "id": "8A382C11-AC78-4ECD-B800-8130B346FFA1"
    },
    {
      "class": "shapeGroup",
      "id": "0D80FA1F-A77E-4333-8E1E-6622D6E9259B"
    },
    {
      "class": "shapeGroup",
      "id": "E99A95E2-25CD-471A-B2EF-A362FA37A9A6"
    },
    {
      "class": "shapeGroup",
      "id": "41490A5F-8454-435F-B431-916F3A74ECCD"
    },
    {
      "class": "shapeGroup",
      "id": "940166B1-C128-4F3E-8370-5BCE4FAD24AF"
    }
  ],
  "name": "Imported Layers Copy 6",
  "nameIsFixed": false,
  "resizingConstraint": 63,
  "resizingType": 0,
  "rotation": 0,
  "shouldBreakMaskChain": false,
  "style": {
    "_class": "style",
    "endDecorationType": 0,
    "miterLimit": 10,
    "startDecorationType": 0
  }
}