{
  "_class": "group",
  "do_objectID": "890F9D78-CF22-4328-8154-0EE5A200E4B5",
  "exportOptions": {
    "_class": "exportOptions",
    "exportFormats": [
    ],
    "includedLayerIds": [
    ],
    "layerOptions": 0,
    "shouldTrim": false
  },
  "frame": {
    "_class": "rect",
    "constrainProportions": false,
    "height": 431,
    "width": 379,
    "x": -2,
    "y": 4271
  },
  "hasClickThrough": false,
  "isFlippedHorizontal": false,
  "isFlippedVertical": false,
  "isLocked": false,
  "isVisible": true,
  "layerListExpandedType": 2,
  "layers": [
    {
      "class": "shapeGroup",
      "id": "E5F951B4-7EFA-4F98-8388-FD4AC142795A"
    },
    {
      "class": "group",
      "id": "96829843-9510-4AB1-B519-8B50E9E01F9B"
    },
    {
      "class": "text",
      "id": "0D28BDDC-2D71-42B0-B931-1E02B5A384B5"
    },
    {
      "class": "group",
      "id": "85EF86F8-B944-474D-9D33-E5E8781F0EA9"
    }
  ],
  "name": "Section / Status Check",
  "nameIsFixed": true,
  "resizingConstraint": 63,
  "resizingType": 0,
  "rotation": 0,
  "shouldBreakMaskChain": false,
  "style": {
    "_class": "style",
    "endDecorationType": 0,
    "miterLimit": 10,
    "startDecorationType": 0
  }
}